securevector/__init__.py
securevector/async_client.py
securevector/cli.py
securevector/cli_enhanced.py
securevector/client.py
securevector/streaming.py
securevector/types.py
securevector/core/__init__.py
securevector/core/modes/__init__.py
securevector/core/modes/mode_factory.py
securevector/core/modes/api/__init__.py
securevector/core/modes/api/api_analyzer.py
securevector/core/modes/api/api_cache.py
securevector/core/modes/api/api_mode.py
securevector/core/modes/hybrid/__init__.py
securevector/core/modes/hybrid/hybrid_mode.py
securevector/core/modes/hybrid/smart_router.py
securevector/core/modes/local/__init__.py
securevector/core/modes/local/local_analyzer.py
securevector/core/modes/local/local_cache.py
securevector/core/modes/local/local_mode.py
securevector/mcp/__init__.py
securevector/mcp/__main__.py
securevector/mcp/auth_validator.py
securevector/mcp/server.py
securevector/mcp/config/__init__.py
securevector/mcp/config/server_config.py
securevector/mcp/prompts/__init__.py
securevector/mcp/prompts/templates.py
securevector/mcp/resources/__init__.py
securevector/mcp/resources/policies.py
securevector/mcp/resources/rules.py
securevector/mcp/tools/__init__.py
securevector/mcp/tools/analyze_prompt.py
securevector/mcp/tools/batch_analysis.py
securevector/mcp/tools/threat_stats.py
securevector/models/__init__.py
securevector/models/analysis_result.py
securevector/models/config_models.py
securevector/models/policy_models.py
securevector/models/threat_types.py
securevector/rules/LICENSE_NOTICE.md
securevector/rules/README.md
securevector/rules/RULES_ATTRIBUTION.md
securevector/rules/__init__.py
securevector/rules/community/__init__.py
securevector/rules/community/mitre_patterns.yml
securevector/rules/community/owasp_top10.yml
securevector/rules/community/sv_community_data_extraction.yml
securevector/rules/community/sv_community_essential_patterns.yml
securevector/rules/community/sv_community_harmful_content.yml
securevector_ai_monitor-1.3.1.dist-info/licenses/LICENSE
securevector_ai_monitor-1.3.1.dist-info/licenses/NOTICE
securevector_ai_monitor-1.3.1.dist-info/METADATA
securevector_ai_monitor-1.3.1.dist-info/WHEEL
securevector_ai_monitor-1.3.1.dist-info/entry_points.txt
securevector_ai_monitor-1.3.1.dist-info/top_level.txt
securevector_ai_monitor-1.3.1.dist-info/RECORD
