Metadata-Version: 2.4
Name: securevector-ai-monitor
Version: 1.3.1
Summary: Real-time AI threat monitoring. Protect your apps from prompt injection, leaks, and attacks in just a few lines of code.
Home-page: https://github.com/secure-vector/ai-threat-monitor
Author: SecureVector Team
Project-URL: Bug Reports, https://github.com/secure-vector/ai-threat-monitor/issues
Project-URL: Source, https://github.com/secure-vector/ai-threat-monitor
Project-URL: Documentation, https://docs.securevector.io/ai-threat-monitor
Project-URL: Homepage, https://securevector.io
Keywords: ai security llm prompt-injection threat-detection threat-monitoring openai claude securevector
Classifier: Development Status :: 4 - Beta
Classifier: Intended Audience :: Developers
Classifier: Topic :: Security
Classifier: Topic :: Software Development :: Libraries :: Python Modules
Classifier: License :: OSI Approved :: Apache Software License
Classifier: Programming Language :: Python :: 3
Classifier: Programming Language :: Python :: 3.9
Classifier: Programming Language :: Python :: 3.10
Classifier: Programming Language :: Python :: 3.11
Classifier: Programming Language :: Python :: 3.12
Classifier: Operating System :: OS Independent
Requires-Python: >=3.9
License-File: LICENSE
License-File: NOTICE
Requires-Dist: PyYAML>=5.1
Requires-Dist: requests>=2.25.0
Requires-Dist: aiohttp>=3.8.0
Requires-Dist: typing-extensions>=4.0.0
Requires-Dist: urllib3>=2.6.0
Provides-Extra: mcp
Requires-Dist: mcp>=1.23.0; extra == "mcp"
Requires-Dist: fastmcp>=2.13.0; extra == "mcp"
Provides-Extra: dev
Requires-Dist: pytest>=6.0; extra == "dev"
Requires-Dist: pytest-cov>=3.0; extra == "dev"
Requires-Dist: pytest-xdist>=2.0; extra == "dev"
Requires-Dist: pytest-asyncio>=0.21.0; extra == "dev"
Requires-Dist: black>=22.0; extra == "dev"
Requires-Dist: flake8>=4.0; extra == "dev"
Requires-Dist: isort>=5.0; extra == "dev"
Requires-Dist: mypy>=0.900; extra == "dev"
Requires-Dist: safety>=2.0; extra == "dev"
Requires-Dist: bandit>=1.7; extra == "dev"
Requires-Dist: psutil>=5.8; extra == "dev"
Provides-Extra: benchmark
Requires-Dist: psutil>=5.8; extra == "benchmark"
Requires-Dist: memory-profiler>=0.60; extra == "benchmark"
Provides-Extra: all
Requires-Dist: mcp>=1.23.0; extra == "all"
Requires-Dist: fastmcp>=2.13.0; extra == "all"
Requires-Dist: psutil>=5.8; extra == "all"
Requires-Dist: memory-profiler>=0.60; extra == "all"
Dynamic: author
Dynamic: classifier
Dynamic: description
Dynamic: description-content-type
Dynamic: home-page
Dynamic: keywords
Dynamic: license-file
Dynamic: project-url
Dynamic: provides-extra
Dynamic: requires-dist
Dynamic: requires-python
Dynamic: summary
